polyharmonics/__init__.py
polyharmonics/__main__.py
polyharmonics/associated_legendre_functions.py
polyharmonics/cli/__init__.py
polyharmonics/cli/associated_legendre_cmd.py
polyharmonics/cli/benchmark/__init__.py
polyharmonics/cli/benchmark/associated_legendre_bench.py
polyharmonics/cli/benchmark/legendre_bench.py
polyharmonics/cli/benchmark/spherical_harmonic_bench.py
polyharmonics/cli/benchmark_cmd.py
polyharmonics/cli/colors.py
polyharmonics/cli/legendre_cmd.py
polyharmonics/cli/plot2d_cmd.py
polyharmonics/cli/plotbench_cmd.py
polyharmonics/cli/plotsh_cmd.py
polyharmonics/cli/spherical_harmonic_cmd.py
polyharmonics/legendre_polynomials.py
polyharmonics/spherical_harmonics.py
polyharmonics-0.8.1.dist-info/LICENSE
polyharmonics-0.8.1.dist-info/METADATA
polyharmonics-0.8.1.dist-info/WHEEL
polyharmonics-0.8.1.dist-info/entry_points.txt
polyharmonics-0.8.1.dist-info/RECORD
