Metadata-Version: 2.1
Name: polyharmonics
Version: 0.8.1
Summary: Ortogonal polynomials in the unit sphere
Home-page: https://github.com/ComicIvans/polyharmonics
License: BSD-3-Clause
Keywords: python,polynomials,unit sphere,orthogonal polynomials,mathematics,math,legendre polynomials,associated legendre functions,spherical harmonics
Author: Iván Salido Cobo
Author-email: isalidocobo@gmail.com
Requires-Python: >=3.10,<4.0
Classifier: Development Status :: 1 - Planning
Classifier: Intended Audience :: Developers
Classifier: Intended Audience :: Education
Classifier: Intended Audience :: Science/Research
Classifier: License :: OSI Approved :: BSD License
Classifier: License :: OSI Approved :: GNU General Public License v3 or later (GPLv3+)
Classifier: Operating System :: OS Independent
Classifier: Programming Language :: Python :: 3
Classifier: Programming Language :: Python :: 3.10
Classifier: Programming Language :: Python :: 3.11
Classifier: Programming Language :: Python :: 3.12
Classifier: Topic :: Scientific/Engineering :: Mathematics
Classifier: Topic :: Software Development :: Libraries :: Python Modules
Requires-Dist: matplotlib (>=3.8.4,<4.0.0)
Requires-Dist: numpy (>=1.26.4,<2.0.0)
Requires-Dist: pandas (>=2.2.2,<3.0.0)
Requires-Dist: rich (>=13.7.1,<14.0.0)
Requires-Dist: scipy (>=1.13.1,<2.0.0)
Requires-Dist: sympy (>=1.12,<2.0)
Requires-Dist: tabulate (>=0.9.0,<0.10.0)
Requires-Dist: typer (>=0.12.3,<0.13.0)
Project-URL: Repository, https://github.com/ComicIvans/polyharmonics
